pdf2markdown4llm/__init__.py
pdf2markdown4llm/pdf2markdown4llm.py
pdf2markdown4llm/tests/test.py
pdf2markdown4llm-0.1.9.dist-info/LICENSE
pdf2markdown4llm-0.1.9.dist-info/METADATA
pdf2markdown4llm-0.1.9.dist-info/WHEEL
pdf2markdown4llm-0.1.9.dist-info/top_level.txt
pdf2markdown4llm-0.1.9.dist-info/RECORD
