Metadata-Version: 2.2
Name: pdf2markdown4llm
Version: 0.1.9
Summary: A library to convert PDF files to Markdown format.
Author-email: HawkClaws <hogehoge@example.com>
License: MIT License
Project-URL: Homepage, https://github.com/HawkClaws/pdf2markdown4llm
Classifier: Programming Language :: Python :: 3
Classifier: License :: OSI Approved :: MIT License
Classifier: Operating System :: OS Independent
Requires-Python: >=3.7
License-File: LICENSE
Requires-Dist: pdfplumber>=0.10
